{
  "meta": {
    "version": "1.1.0",
    "type": "diagnosis_questionnaire",
    "languages": ["en", "kr"]
  },
  "sections": [
    {
      "id": "oil",
      "title": "Oily vs Dry (Hydration)",
      "questions": [
        {
          "id": "Q01",
          "locales": {
            "en": {
              "text": "How does your face feel 2-3 hours after washing without moisturizer?",
              "options": [
                { "text": "Very rough, flaky", "score": { "oil": 0 } },
                { "text": "Tight", "score": { "oil": 10 } },
                { "text": "Normal", "score": { "oil": 20 } },
                { "text": "Shiny", "score": { "oil": 30 } }
              ]
            },
            "kr": {
              "text": "세안 후 로션을 바르지 않고 2~3시간이 지났을 때, 피부 느낌은 어떤가요?",
              "options": [
                { "text": "매우 거칠고 하얗게 일어남 (각질)", "score": { "oil": 0 } },
                { "text": "당김이 심하게 느껴짐", "score": { "oil": 10 } },
                { "text": "당기지도 번들거리지도 않음 (편안함)", "score": { "oil": 20 } },
                { "text": "번들거림 (기름기가 돎)", "score": { "oil": 30 } }
              ]
            }
          }
        },
        {
          "id": "Q08",
          "trapKey": "wash_tightness",
          "locales": {
            "en": {
              "text": "After washing your face, does it feel tight immediately?",
              "options": [
                { "text": "Yes, very tight", "value": true, "score": { "oil": 0 } },
                { "text": "No, comfortable", "value": false, "score": { "oil": 10 } }
              ]
            },
            "kr": {
              "text": "세안 직후 피부가 바로 당기나요?",
              "options": [
                { "text": "네, 매우 당깁니다", "value": true, "score": { "oil": 0 } },
                { "text": "아니오, 편안합니다", "value": false, "score": { "oil": 10 } }
              ]
            }
          }
        },
        {
          "id": "Q09",
          "locales": {
            "en": {
              "text": "Look at your T-zone in the mirror at 3 PM. Is it shiny?",
              "options": [
                { "text": "No", "score": { "oil": 0 } },
                { "text": "A little", "score": { "oil": 10 } },
                { "text": "Yes, very shiny", "score": { "oil": 20 } }
              ]
            },
            "kr": {
              "text": "오후 3시쯤 거울을 봤을 때, T존(이마, 코)이 번들거리나요?",
              "options": [
                { "text": "아니오 (매트함)", "score": { "oil": 0 } },
                { "text": "약간 번들거림 (광이 남)", "score": { "oil": 10 } },
                { "text": "네, 매우 번들거림 (기름종이 필요)", "score": { "oil": 20 } }
              ]
            }
          }
        },
        {
          "id": "Q10",
          "trapKey": "pore_size",
          "locales": {
            "en": {
              "text": "How would you describe your pore size?",
              "options": [
                { "text": "Invisible (Small)", "value": "Small", "score": { "oil": 0 } },
                { "text": "Visible only in T-zone (Medium)", "value": "Medium", "score": { "oil": 10 } },
                { "text": "Visible everywhere (Large)", "value": "Large", "score": { "oil": 20 } }
              ]
            },
            "kr": {
              "text": "모공 크기는 어떤가요?",
              "options": [
                { "text": "거의 안 보임 (작음)", "value": "Small", "score": { "oil": 0 } },
                { "text": "T존 위주로 보임 (보통)", "value": "Medium", "score": { "oil": 10 } },
                { "text": "얼굴 전체적으로 잘 보임 (큼)", "value": "Large", "score": { "oil": 20 } }
              ]
            }
          }
        },
        {
          "id": "TRAP_01",
          "trapKey": "oil_check",
          "locales": {
            "en": {
              "text": "Do you feel your skin is oily on the surface but dry/tight inside?",
              "options": [
                 { "text": "Yes", "value": true },
                 { "text": "No", "value": false }
              ]
            },
            "kr": {
              "text": "피부 겉은 번들거리는데 속은 당기는 느낌(수부지)이 있나요?",
              "options": [
                 { "text": "네", "value": true },
                 { "text": "아니오", "value": false }
              ]
            }
          }
        }
      ]
    },
    {
      "id": "sensitivity",
      "title": "Sensitivity",
      "questions": [
        {
          "id": "TRAP_02",
          "trapKey": "sensitive_check",
          "locales": {
            "en": {
              "text": "Do you often get red or stinging skin after using new cosmetics?",
              "options": [
                { "text": "Yes", "value": true, "score": { "sensitivity": 20 } },
                { "text": "No", "value": false, "score": { "sensitivity": 0 } }
              ]
            },
            "kr": {
              "text": "새 화장품을 쓰면 자주 피부가 붉어지거나 따갑나요?",
              "options": [
                { "text": "네", "value": true, "score": { "sensitivity": 20 } },
                { "text": "아니오", "value": false, "score": { "sensitivity": 0 } }
              ]
            }
          }
        }
      ]
    }
  ]
}
